secutils/__init__.py
secutils/download_sec.py
secutils/edgar.py
secutils/utils.py
secutils-0.0.3.dist-info/LICENSE.txt
secutils-0.0.3.dist-info/METADATA
secutils-0.0.3.dist-info/WHEEL
secutils-0.0.3.dist-info/top_level.txt
secutils-0.0.3.dist-info/RECORD
