Metadata-Version: 2.1
Name: secutils
Version: 0.0.3
Summary: Download SEC files in bulk
Home-page: https://github.com/datawrestler/sec-utils
Author: Jason Lewris, Steve To, Tyler Lewris
Author-email: datawrestler@gmail.com
License: UNKNOWN
Platform: UNKNOWN
Classifier: Programming Language :: Python :: 3
Classifier: License :: OSI Approved :: MIT License
Classifier: Operating System :: OS Independent
Requires-Python: >=3.6
